flask_moment/__init__.py
Flask_Moment-1.0.6.dist-info/LICENSE
Flask_Moment-1.0.6.dist-info/METADATA
Flask_Moment-1.0.6.dist-info/WHEEL
Flask_Moment-1.0.6.dist-info/top_level.txt
Flask_Moment-1.0.6.dist-info/RECORD
