Metadata-Version: 2.1
Name: Flask-Moment
Version: 1.0.6
Summary: Formatting of dates and times in Flask templates using moment.js.
Author-email: Miguel Grinberg <miguel.grinberg@gmail.com>
Project-URL: Homepage, https://github.com/miguelgrinberg/flask-moment
Project-URL: Bug Tracker, https://github.com/miguelgrinberg/flask-moment/issues
Classifier: Intended Audience :: Developers
Classifier: Programming Language :: Python :: 3
Classifier: License :: OSI Approved :: MIT License
Classifier: Operating System :: OS Independent
Requires-Python: >=3.6
License-File: LICENSE
Requires-Dist: Flask
Requires-Dist: packaging>=14.1
Provides-Extra: docs
Requires-Dist: sphinx; extra == "docs"
